simple_ai/__init__.py
simple_ai/hf_backend.py
simple_ai/model.py
simple_ai/model_hf.py
simple_ai/onnx_backend.py
simple_ai/tokenizer_hf.py
simpleai_sdk-0.1.1.dist-info/licenses/LICENSE
simpleai_sdk-0.1.1.dist-info/METADATA
simpleai_sdk-0.1.1.dist-info/WHEEL
simpleai_sdk-0.1.1.dist-info/top_level.txt
simpleai_sdk-0.1.1.dist-info/RECORD
