Metadata-Version: 2.4
Name: simpleai-sdk
Version: 0.1.1
Summary: A simple, high-level Python package for the Lille language model.
Author: Nikityyy
License: Apache License (2.0)
Project-URL: Homepage, https://github.com/Nikityyy/simple-ai
Project-URL: Bug Tracker, https://github.com/Nikityyy/simple-ai/issues
Keywords: llm,language model,ai,onnx,transformers,huggingface
Classifier: Programming Language :: Python :: 3
Classifier: License :: OSI Approved :: Apache Software License
Classifier: Operating System :: OS Independent
Classifier: Intended Audience :: Developers
Classifier: Intended Audience :: Science/Research
Classifier: Topic :: Scientific/Engineering :: Artificial Intelligence
Requires-Python: >=3.8
License-File: LICENSE
Dynamic: license-file
